clickhouse_arrow/__init__.py
clickhouse_arrow-0.5.0.dist-info/WHEEL
clickhouse_arrow-0.5.0.dist-info/METADATA
clickhouse_arrow-0.5.0.dist-info/RECORD
