Metadata-Version: 2.3
Name: clickhouse-arrow
Version: 0.5.0
Summary: A minimal client that uses the ClickHouse HTTP API and Apache Arrow.
Author: Martin Galpin
Author-email: Martin Galpin <galpin@galpin.com>
Requires-Dist: pyarrow>=11.0.0
Requires-Dist: urllib3<2.0.0
Requires-Python: >=3.10
